beautiful_captions/__init__.py
beautiful_captions/core/caption.py
beautiful_captions/core/config.py
beautiful_captions/core/video.py
beautiful_captions/fonts/CheGuevaraBarry-Brown.ttf
beautiful_captions/fonts/FiraSansCondensed-ExtraBoldItalic.ttf
beautiful_captions/fonts/Gabarito-Black.ttf
beautiful_captions/fonts/KOMIKAX_.ttf
beautiful_captions/fonts/Montserrat-Bold.ttf
beautiful_captions/fonts/Proxima-Nova-Semibold.ttf
beautiful_captions/fonts/Rubik-ExtraBold.ttf
beautiful_captions/styling/animation.py
beautiful_captions/styling/style.py
beautiful_captions/transcription/assemblyai.py
beautiful_captions/transcription/base.py
beautiful_captions/transcription/deepgram.py
beautiful_captions/transcription/openai.py
beautiful_captions/utils/ffmpeg.py
beautiful_captions/utils/subtitles.py
beautiful_captions-0.1.70.dist-info/licenses/LICENSE
beautiful_captions-0.1.70.dist-info/METADATA
beautiful_captions-0.1.70.dist-info/WHEEL
beautiful_captions-0.1.70.dist-info/top_level.txt
beautiful_captions-0.1.70.dist-info/RECORD
