Metadata-Version: 2.4
Name: beautiful-captions
Version: 0.1.70
Summary: A fast and elegant Python library for adding beautiful captions to videos
Author-email: Aayush <aayugupta04@gmail.com>
License: MIT License
Project-URL: Homepage, https://github.com/aayushgupta16/beautiful-captions
Project-URL: Repository, https://github.com/aayushgupta16/beautiful-captions.git
Project-URL: Documentation, https://beautiful-captions.readthedocs.io/
Project-URL: Bug Tracker, https://github.com/aayushgupta16/beautiful-captions/issues
Keywords: video,captions,subtitles,transcription
Classifier: Development Status :: 3 - Alpha
Classifier: Intended Audience :: Developers
Classifier: License :: OSI Approved :: MIT License
Classifier: Programming Language :: Python :: 3
Classifier: Programming Language :: Python :: 3.8
Classifier: Programming Language :: Python :: 3.9
Classifier: Programming Language :: Python :: 3.10
Classifier: Programming Language :: Python :: 3.11
Requires-Python: >=3.8
License-File: LICENSE
Requires-Dist: pysrt>=1.1.2
Requires-Dist: assemblyai>=0.17.0
Requires-Dist: deepgram-sdk>=2.11.0
Requires-Dist: openai>=1.0.0
Requires-Dist: python-dotenv>=0.19.0
Requires-Dist: aiohttp>=3.8.0
Requires-Dist: ffmpeg-python>=0.2.0
Dynamic: license-file
Dynamic: requires-python
